parareq/__init__.py
parareq/parareq.py
parareq-0.1.0.dist-info/LICENSE
parareq-0.1.0.dist-info/METADATA
parareq-0.1.0.dist-info/WHEEL
parareq-0.1.0.dist-info/RECORD
