Metadata-Version: 2.1
Name: parareq
Version: 0.1.0
Summary: Reliable Parallel OpenAI API Request Processing with Rate Limiting
License: MIT
Author: Matt Gibson
Requires-Python: >=3.11,<4.0
Classifier: License :: OSI Approved :: MIT License
Classifier: Programming Language :: Python :: 3
Classifier: Programming Language :: Python :: 3.11
